ml_optimizers/__init__.py
ml_optimizers/text_reader.py
ml_optimizers/data/my_code.py
ml_optimizers-0.1.dist-info/METADATA
ml_optimizers-0.1.dist-info/WHEEL
ml_optimizers-0.1.dist-info/top_level.txt
ml_optimizers-0.1.dist-info/RECORD
