Metadata-Version: 2.1
Name: ml-optimizers
Version: 0.1
Summary: Code for All Optimizers with Plots
Home-page: https://github.com/savioratharv/prac_testing
Author: davinci003
Author-email: freegpt00@gmail.com
